[
  {
    "id": 1,
    "name": "Sukanta Dhar",
    "username": "dhar",
    "email": "sukanta@dhar.in",
    "address": {
      "city": "Ahmedabad"
    },
    "company": {
      "name": "TKS Technology"
    }
  },
  {
    "id": 2,
    "name": "Irene Paul",
    "username": "irene",
    "email": "irene@paul.in",
    "address": {
     "city": "Lucknow" 
    },
    "company": {
      "name": "SKF Technology"
    }
  },
  {
    "id": 3,
    "name": "John De",
    "username": "Bret",
    "email": "john@paul.in",
    "address": {
     "city": "Mumbai" 
    },
      "company": {
      "name": "Boring Company"
    }
  },
  {
    "id": 4,
    "name": "Neel Patel",
    "username": "neel",
    "email": "neel@patel.in",
    "address": {
      "city": "Pune" 
    },
     "company": {
      "name": "Neel Patel"
    }
  },
  {
    "id": 5,
    "name": "Akshay Pilot",
    "username": "Kamren",
    "email": "akshay@pilot.in",
    "address": {
       "city": "Kolkata" 
    },
     "company": {
      "name": "HARMAN LLP"
    }
  },
  {
    "id": 6,
    "name": "Sukbir Iot",
    "username": "Leopoldo_Corkery",
    "email": "sukbir@iot.in",
    "address": {
      "city": "Chandigarh"
    },
    "company": {
      "name": "Sukrit-iot"
    }
  },
  {
    "id": 7,
    "name": "Kirti Debbarma",
    "username": "kirti.debbarma",
    "email": "kirti@debbarma.in",
    "address": {
      "city": "Chennai"
    },
    "company": {
      "name": "Johns n Johnson"
    }
  },
  {
    "id": 8,
    "name": "Kirti Rao",
    "username": "Maxime_Nienow",
    "email": "kirti@rao.in",
    "address": {
      "city": "Pune"
    },
    "company": {
      "name": "Ambi Pure"
    }
  },
  {
    "id": 9,
    "name": "Guliya Ram",
    "username": "Delphine",
    "email": "guliya@ram.io",
    "address": {
      "city": "Goa"
    },
    "company": {
      "name": "Yum Sum Technology"

    }
  },
  {
    "id": 10,
    "name": "Cliyopetra Das",
    "username": "Moriah.Stanton",
    "email": "cliyo.das@das.in",
    "address": {
      "city": "Goa"
    },
    "company": {
      "name": "Hoeger LLC"
    }
  }
]